wsi_normalizer/__init__.py
wsi_normalizer/norm_tools.py
wsi_normalizer/utils.py
wsi_normalizer/torchvahadane/__init__.py
wsi_normalizer/torchvahadane/dict_learning.py
wsi_normalizer/torchvahadane/eps.py
wsi_normalizer/torchvahadane/histogram_matching.py
wsi_normalizer/torchvahadane/optimizers.py
wsi_normalizer/torchvahadane/stain_extractor_cpu.py
wsi_normalizer/torchvahadane/stain_extractor_gpu.py
wsi_normalizer/torchvahadane/torchvahadane.py
wsi_normalizer/torchvahadane/utils.py
wsi_normalizer/torchvahadane/wsi_util.py
wsi_normalizer-1.0.1.dist-info/licenses/LICENSE
wsi_normalizer-1.0.1.dist-info/._PKG-INFO
wsi_normalizer-1.0.1.dist-info/._SOURCES.txt
wsi_normalizer-1.0.1.dist-info/._dependency_links.txt
wsi_normalizer-1.0.1.dist-info/._requires.txt
wsi_normalizer-1.0.1.dist-info/._top_level.txt
wsi_normalizer-1.0.1.dist-info/METADATA
wsi_normalizer-1.0.1.dist-info/WHEEL
wsi_normalizer-1.0.1.dist-info/top_level.txt
wsi_normalizer-1.0.1.dist-info/RECORD
