Metadata-Version: 2.4
Name: wsi-normalizer
Version: 1.0.1
Summary: A tool used for whole slide images normalization, support macenko, reinhard, vahadane (GPU accelerate)
Author-email: Haoyu Cui <haoyuchui@gmail.com>
License: MIT License
Project-URL: Homepage, https://github.com/HaoyuCui/WSI_Normalizer
Classifier: Programming Language :: Python :: 3
Classifier: License :: OSI Approved :: MIT License
Classifier: Operating System :: OS Independent
Requires-Python: >=3.6
License-File: LICENSE
Requires-Dist: numpy>=1.13.3
Requires-Dist: opencv-python>=3.2.0
Requires-Dist: scikit-image>=0.14.0
Requires-Dist: scikit-learn>=0.20.0
Requires-Dist: tqdm>=4.0.0
Requires-Dist: Pillow>=4.0.0
Requires-Dist: matplotlib>=2.0.0
Requires-Dist: spams-bin
Dynamic: license-file
